IdenDSS/IDSS.py
IdenDSS/__init__.py
IdenDSS/__main__.py
IdenDSS/identification.py
IdenDSS/plugins.py
IdenDSS/primer_utils.py
IdenDSS/utils.py
IdenDSS/validation.py
IdenDSS/template/DSS_settings.txt
IdenDSS/template/GUI.settings.json
IdenDSS-0.2.6.dist-info/LICENSE
IdenDSS-0.2.6.dist-info/METADATA
IdenDSS-0.2.6.dist-info/WHEEL
IdenDSS-0.2.6.dist-info/entry_points.txt
IdenDSS-0.2.6.dist-info/top_level.txt
IdenDSS-0.2.6.dist-info/RECORD
