Metadata-Version: 2.1
Name: IdenDSS
Version: 0.2.6
Summary: DNA Signature Sequence (DSS) Identification and Application Software
Home-page: https://github.com/Hua-CM/IdenDSS
Author: Zhongyi Hua
Author-email: njbxhzy@hotmail.com
Classifier: Programming Language :: Python :: 3
Classifier: License :: OSI Approved :: GNU General Public License v3 or later (GPLv3+)
Classifier: Operating System :: OS Independent
Requires-Python: >=3.8
License-File: LICENSE
Requires-Dist: biopython (>=1.78)
Requires-Dist: pandas (>=1.0.0)
Requires-Dist: numpy (>=1.20.0)
